manage.py
django_protoni-0.5.2.data/scripts/manage.py
protoni/__init__.py
protoni/asetukset.py
protoni/asgi.py
protoni/nakymat.py
protoni/osoitteet.py
protoni/palvelimet.py
protoni/palvelin.py
protoni/salaus.py
protoni/tyoasema.py
protoni/wsgi.py
protoni/laajennos/__init__.py
protoni/laajennos/celery.py
protoni/laajennos/corsheaders.py
protoni/laajennos/debug_toolbar.py
protoni/laajennos/dj_database_url.py
protoni/laajennos/extensions.py
protoni/laajennos/heroku.py
protoni/laajennos/hosts.py
protoni/laajennos/pipeline.py
protoni/laajennos/sentry.py
protoni/laajennos/whitenoise.py
django_protoni-0.5.2.dist-info/METADATA
django_protoni-0.5.2.dist-info/WHEEL
django_protoni-0.5.2.dist-info/entry_points.txt
django_protoni-0.5.2.dist-info/historia.json
django_protoni-0.5.2.dist-info/top_level.txt
django_protoni-0.5.2.dist-info/RECORD
